tracept/__init__.py
tracept/core.py
tracept/interp.py
tracept/odes.py
tracept-0.0.1.dist-info/METADATA
tracept-0.0.1.dist-info/WHEEL
tracept-0.0.1.dist-info/licenses/LICENSE
tracept-0.0.1.dist-info/RECORD
