Metadata-Version: 2.4
Name: tracept
Version: 0.0.1
Summary: JIT-compile-time utilities for cleaner JAX code, with extra utilities for dynamic systems.
Project-URL: Homepage, https://github.com/tscott-00/tracept
Author: Thomas A. Scott
License-File: LICENSE
Requires-Python: >=3.10
Requires-Dist: jax
Requires-Dist: jaxlib
Requires-Dist: numpy
